mediagrains_s3/__init__.py
mediagrains_s3/__main__.py
mediagrains_s3/bucket.py
mediagrains_s3/progresstrackers.py
mediagrains_s3/s3/__init__.py
mediagrains_s3/s3/encoder.py
mediagrains_s3/s3/gsfs3bucket.py
mediagrains_s3/swift/__init__.py
mediagrains_s3/swift/encoder.py
mediagrains_s3/swift/gsfswiftbucket.py
mediagrains_s3-0.4.0.dist-info/METADATA
mediagrains_s3-0.4.0.dist-info/WHEEL
mediagrains_s3-0.4.0.dist-info/top_level.txt
mediagrains_s3-0.4.0.dist-info/RECORD
