Metadata-Version: 2.1
Name: mediagrains-s3
Version: 0.4.0
Summary: A library for reading and writing mediagrains to and from object storage
Home-page: https://github.com/bbc/rd-apmm-python-lib-mediagrains-s3
Author: James P. Weaver
Author-email: james.barrett@bbc.co.uk
License: UNKNOWN
Platform: UNKNOWN
Requires-Dist: six (>=1.11.0)
Requires-Dist: mediagrains (>=0.1.1)
Requires-Dist: boto3 (>=1.6.12)
